pycbrf/__init__.py
pycbrf/banks.py
pycbrf/cli.py
pycbrf/exceptions.py
pycbrf/rates.py
pycbrf/toolbox.py
pycbrf/utils.py
pycbrf-1.1.0.dist-info/AUTHORS
pycbrf-1.1.0.dist-info/LICENSE
pycbrf-1.1.0.dist-info/METADATA
pycbrf-1.1.0.dist-info/WHEEL
pycbrf-1.1.0.dist-info/entry_points.txt
pycbrf-1.1.0.dist-info/top_level.txt
pycbrf-1.1.0.dist-info/RECORD
