Metadata-Version: 2.1
Name: pycbrf
Version: 1.1.0
Summary: Tools to query Bank of Russia
Home-page: https://github.com/idlesign/pycbrf
Author: Igor `idle sign` Starikov
Author-email: idlesign@yandex.ru
License: BSD 3-Clause License
Platform: UNKNOWN
Classifier: Development Status :: 5 - Production/Stable
Classifier: Operating System :: OS Independent
Classifier: Programming Language :: Python
Classifier: Programming Language :: Python :: 3
Classifier: Programming Language :: Python :: 3.6
Classifier: Programming Language :: Python :: 3.7
Classifier: Programming Language :: Python :: 3.8
Classifier: Programming Language :: Python :: 3.9
Classifier: License :: OSI Approved :: BSD License
Requires-Dist: requests
Requires-Dist: dbf-light (>=0.3.0)
Provides-Extra: cli
Requires-Dist: click ; extra == 'cli'
